src/hw/lut-coloring/table_color.sv
module table_color(
    input logic [9:0] depth, max_iterations,
    input logic clk,
    input logic en,
    output logic [23:0] color
);
    logic escape;
    logic [23:0] color_lut [0:1023];

    // Intermediate variables
    logic [19:0] scaled_mult;
   // verilator lint_off UNUSED
	logic [19:0] div_result;
// verilator lint_on UNUSED
    logic [9:0] address;

    assign escape = (depth != max_iterations);
    assign scaled_mult = depth * 10'd1023;
    assign div_result = (max_iterations != 0) ? (scaled_mult / {{10{1'b0}},max_iterations}) : 20'd0;
    assign address = div_result[9:0]; // safely truncate to 10 bits

    initial $readmemh("color_lut.txt", color_lut);

    always_ff @(posedge clk) begin
        if (en) begin
            if (!escape)
                color <= 24'h000000;
            else
                color <= color_lut[address];
        end
    end
endmodule

src/hw/lut-coloring/table_color.vcd
$version Generated by VerilatedVcd $end
$date Thu May 22 15:59:58 2025 $end
$timescale 1ps $end

 $scope module TOP $end
  $var wire  1 % clk $end
  $var wire 24 ' color [23:0] $end
  $var wire 10 # depth [9:0] $end
  $var wire  1 & en $end
  $var wire 10 $ max_iterations [9:0] $end
  $scope module table_color $end
   $var wire 10 + address [9:0] $end
   $var wire  1 % clk $end
   $var wire 24 ' color [23:0] $end
   $var wire 10 # depth [9:0] $end
   $var wire 20 * div_result [19:0] $end
   $var wire  1 & en $end
   $var wire  1 ( escape $end
   $var wire 10 $ max_iterations [9:0] $end
   $var wire 20 ) scaled_mult [19:0] $end
  $upscope $end
 $upscope $end
$enddefinitions $end


#0
b0000000000 #
b0001100100 $
0%
0&
b000000000000000000000000 '
1(
b00000000000000000000 )
b00000000000000000000 *
b0000000000 +
#1
1%
#2
b0000000001 #
0%
b00000000001111111111 )
b00000000000000001010 *
b0000001010 +
#3
1%
#4
b0000000010 #
0%
b00000000011111111110 )
b00000000000000010100 *
b0000010100 +
#5
1%
#6
b0000000011 #
0%
b00000000101111111101 )
b00000000000000011110 *
b0000011110 +
#7
1%
#8
b0000000100 #
0%
b00000000111111111100 )
b00000000000000101000 *
b0000101000 +
#9
1%
#10
b0000000101 #
0%
1&
b00000001001111111011 )
b00000000000000110011 *
b0000110011 +
#11
1%
b000001100000010000011011 '
#12
b0000000110 #
0%
b00000001011111111010 )
b00000000000000111101 *
b0000111101 +
#13
1%
b000010010000011000100001 '
#14
b0000000111 #
0%
b00000001101111111001 )
b00000000000001000111 *
b0001000111 +
#15
1%
b000010110000011100100110 '
#16
b0000001000 #
0%
b00000001111111111000 )
b00000000000001010001 *
b0001010001 +
#17
1%
b000011110000100100101101 '
#18
b0000001001 #
0%
b00000010001111110111 )
b00000000000001011100 *
b0001011100 +
#19
1%
b000100110000101000110100 '
#20
b0000001010 #
0%
b00000010011111110110 )
b00000000000001100110 *
b0001100110 +
#21
1%
b000101100000101100111001 '
#22
b0000001011 #
0%
b00000010101111110101 )
b00000000000001110000 *
b0001110000 +
#23
1%
b000110100000101101000000 '
#24
b0000001100 #
0%
b00000010111111110100 )
b00000000000001111010 *
b0001111010 +
#25
1%
b000111010000110001000101 '
#26
b0000001101 #
0%
b00000011001111110011 )
b00000000000010000100 *
b0010000100 +
#27
1%
b001000100000101101001100 '
#28
b0000001110 #
0%
b00000011011111110010 )
b00000000000010001111 *
b0010001111 +
#29
1%
b001001100000101101010000 '
#30
b0000001111 #
0%
b00000011101111110001 )
b00000000000010011001 *
b0010011001 +
#31
1%
b001010110000101001010110 '
#32
b0000010000 #
0%
b00000011111111110000 )
b00000000000010100011 *
b0010100011 +
#33
1%
b001011100000101001011010 '
#34
b0000010001 #
0%
b00000100001111101111 )
b00000000000010101101 *
b0010101101 +
#35
1%
b001101000000100101011111 '
#36
b0000010010 #
0%
b00000100011111101110 )
b00000000000010111000 *
b0010111000 +
#37
1%
b001110010000100101100010 '
#38
b0000010011 #
0%
b00000100101111101101 )
b00000000000011000010 *
b0011000010 +
#39
1%
b001111000000100101100101 '
#40
b0000010100 #
0%
b00000100111111101100 )
b00000000000011001100 *
b0011001100 +
#41
1%
b010000010000100101100111 '
#42
b0000010101 #
0%
b00000101001111101011 )
b00000000000011010110 *
b0011010110 +
#43
1%
b010001010000101001101001 '
#44
b0000010110 #
0%
b00000101011111101010 )
b00000000000011100001 *
b0011100001 +
#45
1%
b010010100000101101101010 '
#46
b0000010111 #
0%
b00000101101111101001 )
b00000000000011101011 *
b0011101011 +
#47
1%
b010011010000110001101011 '
#48
b0000011000 #
0%
b00000101111111101000 )
b00000000000011110101 *
b0011110101 +
#49
1%
b010100100000111001101100 '
#50
b0000011001 #
0%
b00000110001111100111 )
b00000000000011111111 *
b0011111111 +
#51
1%
b010101010000111101101101 '
#52
b0000011010 #
0%
b00000110011111100110 )
b00000000000100001001 *
b0100001001 +
#53
1%
b010110100001000101101101 '
#54
b0000011011 #
0%
b00000110101111100101 )
b00000000000100010100 *
b0100010100 +
#55
1%
b010111110001001001101110 '
#56
b0000011100 #
0%
b00000110111111100100 )
b00000000000100011110 *
b0100011110 +
#57
1%
b011000100001010001101110 '
#58
b0000011101 #
0%
b00000111001111100011 )
b00000000000100101000 *
b0100101000 +
#59
1%
b011001100001010101101110 '
#60
b0000011110 #
0%
b00000111011111100010 )
b00000000000100110010 *
b0100110010 +
#61
1%
b011010100001011101101110 '
#62
b0000011111 #
0%
b00000111101111100001 )
b00000000000100111101 *
b0100111101 +
#63
1%
b011011100001100001101110 '
#64
b0000100000 #
0%
b00000111111111100000 )
b00000000000101000111 *
b0101000111 +
#65
1%
b011100100001100101101101 '
#66
b0000100001 #
0%
b00001000001111011111 )
b00000000000101010001 *
b0101010001 +
#67
1%
b011101100001101101101101 '
#68
b0000100010 #
0%
b00001000011111011110 )
b00000000000101011011 *
b0101011011 +
#69
1%
b011110100001110001101101 '
#70
b0000100011 #
0%
b00001000101111011101 )
b00000000000101100110 *
b0101100110 +
#71
1%
b011111100001111001101100 '
#72
b0000100100 #
0%
b00001000111111011100 )
b00000000000101110000 *
b0101110000 +
#73
1%
b100000110010000001101011 '
#74
b0000100101 #
0%
b00001001001111011011 )
b00000000000101111010 *
b0101111010 +
#75
1%
b100001100010000101101010 '
#76
b0000100110 #
0%
b00001001011111011010 )
b00000000000110000100 *
b0110000100 +
#77
1%
b100010110010001001101001 '
#78
b0000100111 #
0%
b00001001101111011001 )
b00000000000110001110 *
b0110001110 +
#79
1%
b100011100010010001101000 '
#80
b0000101000 #
0%
b00001001111111011000 )
b00000000000110011001 *
b0110011001 +
#81
1%
b100100110010010101100111 '
#82
b0000101001 #
0%
b00001010001111010111 )
b00000000000110100011 *
b0110100011 +
#83
1%
b100101100010011001100110 '
#84
b0000101010 #
0%
b00001010011111010110 )
b00000000000110101101 *
b0110101101 +
#85
1%
b100110110010100001100100 '
#86
b0000101011 #
0%
b00001010101111010101 )
b00000000000110110111 *
b0110110111 +
#87
1%
b100111100010100101100011 '
#88
b0000101100 #
0%
b00001010111111010100 )
b00000000000111000010 *
b0111000010 +
#89
1%
b101000110010101101100001 '
#90
b0000101101 #
0%
b00001011001111010011 )
b00000000000111001100 *
b0111001100 +
#91
1%
b101001110010110101011111 '
#92
b0000101110 #
0%
b00001011011111010010 )
b00000000000111010110 *
b0111010110 +
#93
1%
b101010110010111001011101 '
#94
b0000101111 #
0%
b00001011101111010001 )
b00000000000111100000 *
b0111100000 +
#95
1%
b101011110011000101011011 '
#96
b0000110000 #
0%
b00001011111111010000 )
b00000000000111101011 *
b0111101011 +
#97
1%
b101100100011001001011001 '
#98
b0000110001 #
0%
b00001100001111001111 )
b00000000000111110101 *
b0111110101 +
#99
1%
b101101110011010001010110 '
#100
b0000110010 #
0%
b00001100011111001110 )
b00000000000111111111 *
b0111111111 +
#101
1%
b101110100011011001010101 '
#102
b0000110011 #
0%
b00001100101111001101 )
b00000000001000001001 *
b1000001001 +
#103
1%
b101111100011100001010010 '
#104
b0000110100 #
0%
b00001100111111001100 )
b00000000001000010011 *
b1000010011 +
#105
1%
b110000010011101001010000 '
#106
b0000110101 #
0%
b00001101001111001011 )
b00000000001000011110 *
b1000011110 +
#107
1%
b110001010011110101001101 '
#108
b0000110110 #
0%
b00001101011111001010 )
b00000000001000101000 *
b1000101000 +
#109
1%
b110010010011111101001010 '
#110
b0000110111 #
0%
b00001101101111001001 )
b00000000001000110010 *
b1000110010 +
#111
1%
b110011000100000101001000 '
#112
b0000111000 #
0%
b00001101111111001000 )
b00000000001000111100 *
b1000111100 +
#113
1%
b110100000100010101000100 '
#114
b0000111001 #
0%
b00001110001111000111 )
b00000000001001000111 *
b1001000111 +
#115
1%
b110100100100011101000010 '
#116
b0000111010 #
0%
b00001110011111000110 )
b00000000001001010001 *
b1001010001 +
#117
1%
b110101100100101000111111 '
#118
b0000111011 #
0%
b00001110101111000101 )
b00000000001001011011 *
b1001011011 +
#119
1%
b110110010100110100111101 '
#120
b0000111100 #
0%
b00001110111111000100 )
b00000000001001100101 *
b1001100101 +
#121
1%
b110111000101000000111001 '
#122
b0000111101 #
0%
b00001111001111000011 )
b00000000001001110000 *
b1001110000 +
#123
1%
b110111110101010000110110 '
#124
b0000111110 #
0%
b00001111011111000010 )
b00000000001001111010 *
b1001111010 +
#125
1%
b111000100101011100110011 '
#126
b0000111111 #
0%
b00001111101111000001 )
b00000000001010000100 *
b1010000100 +
#127
1%
b111001010101101100110000 '
#128
b0001000000 #
0%
b00001111111111000000 )
b00000000001010001110 *
b1010001110 +
#129
1%
b111001100101111000101101 '
#130
b0001000001 #
0%
b00010000001110111111 )
b00000000001010011000 *
b1010011000 +
#131
1%
b111010010110001000101010 '
#132
b0001000010 #
0%
b00010000011110111110 )
b00000000001010100011 *
b1010100011 +
#133
1%
b111010110110010100100111 '
#134
b0001000011 #
0%
b00010000101110111101 )
b00000000001010101101 *
b1010101101 +
#135
1%
b111011010110101000100011 '
#136
b0001000100 #
0%
b00010000111110111100 )
b00000000001010110111 *
b1010110111 +
#137
1%
b111011110110110100100001 '
#138
b0001000101 #
0%
b00010001001110111011 )
b00000000001011000001 *
b1011000001 +
#139
1%
b111100010111001000011101 '
#140
b0001000110 #
0%
b00010001011110111010 )
b00000000001011001100 *
b1011001100 +
#141
1%
b111100110111011100011001 '
#142
b0001000111 #
0%
b00010001101110111001 )
b00000000001011010110 *
b1011010110 +
#143
1%
b111101000111101000010110 '
#144
b0001001000 #
0%
b00010001111110111000 )
b00000000001011100000 *
b1011100000 +
#145
1%
b111101101000000000010010 '
#146
b0001001001 #
0%
b00010010001110110111 )
b00000000001011101010 *
b1011101010 +
#147
1%
b111101111000001100010000 '
#148
b0001001010 #
0%
b00010010011110110110 )
b00000000001011110101 *
b1011110101 +
#149
1%
b111110001000100000001100 '
#150
b0001001011 #
0%
b00010010101110110101 )
b00000000001011111111 *
b1011111111 +
#151
1%
b111110011000110000001001 '
#152
b0001001100 #
0%
b00010010111110110100 )
b00000000001100001001 *
b1100001001 +
#153
1%
b111110101001000100000111 '
#154
b0001001101 #
0%
b00010011001110110011 )
b00000000001100010011 *
b1100010011 +
#155
1%
b111110101001010100000110 '
#156
b0001001110 #
0%
b00010011011110110010 )
b00000000001100011101 *
b1100011101 +
#157
1%
b111110111001101100000110 '
#158
b0001001111 #
0%
b00010011101110110001 )
b00000000001100101000 *
b1100101000 +
#159
1%
b111110111010000000000111 '
#160
b0001010000 #
0%
b00010011111110110000 )
b00000000001100110010 *
b1100110010 +
#161
1%
b111110111010010000001010 '
#162
b0001010001 #
0%
b00010100001110101111 )
b00000000001100111100 *
b1100111100 +
#163
1%
b111110111010101000001110 '
#164
b0001010010 #
0%
b00010100011110101110 )
b00000000001101000110 *
b1101000110 +
#165
1%
b111110111010111000010010 '
#166
b0001010011 #
0%
b00010100101110101101 )
b00000000001101010001 *
b1101010001 +
#167
1%
b111110111011001100011000 '
#168
b0001010100 #
0%
b00010100111110101100 )
b00000000001101011011 *
b1101011011 +
#169
1%
b111110111011011100011100 '
#170
b0001010101 #
0%
b00010101001110101011 )
b00000000001101100101 *
b1101100101 +
#171
1%
b111110101011110100100011 '
#172
b0001010110 #
0%
b00010101011110101010 )
b00000000001101101111 *
b1101101111 +
#173
1%
b111110101100000100101000 '
#174
b0001010111 #
0%
b00010101101110101001 )
b00000000001101111010 *
b1101111010 +
#175
1%
b111110011100011100101111 '
#176
b0001011000 #
0%
b00010101111110101000 )
b00000000001110000100 *
b1110000100 +
#177
1%
b111110001100110100110111 '
#178
b0001011001 #
0%
b00010110001110100111 )
b00000000001110001110 *
b1110001110 +
#179
1%
b111101111101000100111100 '
#180
b0001011010 #
0%
b00010110011110100110 )
b00000000001110011000 *
b1110011000 +
#181
1%
b111101011101011101000101 '
#182
b0001011011 #
0%
b00010110101110100101 )
b00000000001110100010 *
b1110100010 +
#183
1%
b111101001101101101001011 '
#184
b0001011100 #
0%
b00010110111110100100 )
b00000000001110101101 *
b1110101101 +
#185
1%
b111100111110000001010110 '
#186
b0001011101 #
0%
b00010111001110100011 )
b00000000001110110111 *
b1110110111 +
#187
1%
b111100101110010001011101 '
#188
b0001011110 #
0%
b00010111011110100010 )
b00000000001111000001 *
b1111000001 +
#189
1%
b111100011110100101101000 '
#190
b0001011111 #
0%
b00010111101110100001 )
b00000000001111001011 *
b1111001011 +
#191
1%
b111100011110110101110000 '
#192
b0001100000 #
0%
b00010111111110100000 )
b00000000001111010110 *
b1111010110 +
#193
1%
b111100011111001001111101 '
#194
b0001100001 #
0%
b00011000001110011111 )
b00000000001111100000 *
b1111100000 +
#195
1%
b111100111111011010001001 '
#196
b0001100010 #
0%
b00011000011110011110 )
b00000000001111101010 *
b1111101010 +
#197
1%
b111101011111100010010001 '
#198
b0001100011 #
0%
b00011000101110011101 )
b00000000001111110100 *
b1111110100 +
#199
1%
b111110011111110010011101 '
#200
b0001100100 #
0%
0(
b00011000111110011100 )
b00000000001111111111 *
b1111111111 +
#201
1%
b000000000000000000000000 '
#202
b0001100101 #
0%
1(
b00011001001110011011 )
b00000000010000001001 *
b0000001001 +
#203
1%
b000000000000000000000110 '
#204
b0001100110 #
0%
b00011001011110011010 )
b00000000010000010011 *
b0000010011 +
#205
1%
b000000010000000100001001 '
#206
b0001100111 #
0%
b00011001101110011001 )
b00000000010000011101 *
b0000011101 +
#207
1%
b000000100000001000010000 '
#208
b0001101000 #
0%
b00011001111110011000 )
b00000000010000100111 *
b0000100111 +
#209
1%
b000001000000001100010100 '
#210
b0001101001 #
0%
b00011010001110010111 )
b00000000010000110010 *
b0000110010 +
#211
1%
b000001100000010000011011 '
#212
b0001101010 #
0%
b00011010011110010110 )
b00000000010000111100 *
b0000111100 +
#213
1%
b000010010000011000100001 '
#214
b0001101011 #
0%
b00011010101110010101 )
b00000000010001000110 *
b0001000110 +
#215
1%
b000010110000011100100110 '
#216
b0001101100 #
0%
b00011010111110010100 )
b00000000010001010000 *
b0001010000 +
#217
1%
b000011110000100100101101 '
#218
b0001101101 #
0%
b00011011001110010011 )
b00000000010001011011 *
b0001011011 +
#219
1%
b000100100000101000110010 '
#220
b0001101110 #
0%
b00011011011110010010 )
b00000000010001100101 *
b0001100101 +
#221
1%
b000101100000101100111001 '
#222
b0001101111 #
0%
b00011011101110010001 )
b00000000010001101111 *
b0001101111 +
#223
1%
b000110010000101100111110 '
#224
b0001110000 #
0%
b00011011111110010000 )
b00000000010001111001 *
b0001111001 +
#225
1%
b000111010000110001000101 '
#226
b0001110001 #
0%
b00011100001110001111 )
b00000000010010000011 *
b0010000011 +
#227
1%
b001000000000110001001010 '
#228
b0001110010 #
0%
b00011100011110001110 )
b00000000010010001110 *
b0010001110 +
#229
1%
b001001100000101101010000 '
#230
b0001110011 #
0%
b00011100101110001101 )
b00000000010010011000 *
b0010011000 +
#231
1%
b001010110000101001010110 '
#232
b0001110100 #
0%
b00011100111110001100 )
b00000000010010100010 *
b0010100010 +
#233
1%
b001011100000101001011010 '
#234
b0001110101 #
0%
b00011101001110001011 )
b00000000010010101100 *
b0010101100 +
#235
1%
b001101000000100101011111 '
#236
b0001110110 #
0%
b00011101011110001010 )
b00000000010010110111 *
b0010110111 +
#237
1%
b001101110000100101100001 '
#238
b0001110111 #
0%
b00011101101110001001 )
b00000000010011000001 *
b0011000001 +
#239
1%
b001111000000100101100101 '
#240
b0001111000 #
0%
b00011101111110001000 )
b00000000010011001011 *
b0011001011 +
#241
1%
b010000000000100101100110 '
#242
b0001111001 #
0%
b00011110001110000111 )
b00000000010011010101 *
b0011010101 +
#243
1%
b010001010000101001101001 '
#244
b0001111010 #
0%
b00011110011110000110 )
b00000000010011100000 *
b0011100000 +
#245
1%
b010010100000101101101010 '
#246
b0001111011 #
0%
b00011110101110000101 )
b00000000010011101010 *
b0011101010 +
#247
1%
b010011010000110001101011 '
#248
b0001111100 #
0%
b00011110111110000100 )
b00000000010011110100 *
b0011110100 +
#249
1%
b010100100000111001101100 '
#250
b0001111101 #
0%
b00011111001110000011 )
b00000000010011111110 *
b0011111110 +
#251
1%
b010101010000111101101101 '
#252
b0001111110 #
0%
b00011111011110000010 )
b00000000010100001000 *
b0100001000 +
#253
1%
b010110100001000101101101 '
#254
b0001111111 #
0%
b00011111101110000001 )
b00000000010100010011 *
b0100010011 +
#255
1%
b010111010001001001101110 '
#256
b0010000000 #
0%
b00011111111110000000 )
b00000000010100011101 *
b0100011101 +
#257
1%
b011000100001010001101110 '
#258
b0010000001 #
0%
b00100000001101111111 )
b00000000010100100111 *
b0100100111 +
#259
1%
b011001010001010101101110 '
#260
b0010000010 #
0%
b00100000011101111110 )
b00000000010100110001 *
b0100110001 +
#261
1%
b011010100001011101101110 '
#262
b0010000011 #
0%
b00100000101101111101 )
b00000000010100111100 *
b0100111100 +
#263
1%
b011011100001100001101110 '
#264
b0010000100 #
0%
b00100000111101111100 )
b00000000010101000110 *
b0101000110 +
#265
1%
b011100100001100101101101 '
#266
b0010000101 #
0%
b00100001001101111011 )
b00000000010101010000 *
b0101010000 +
#267
1%
b011101100001101101101101 '
#268
b0010000110 #
0%
b00100001011101111010 )
b00000000010101011010 *
b0101011010 +
#269
1%
b011110100001110001101101 '
#270
b0010000111 #
0%
b00100001101101111001 )
b00000000010101100101 *
b0101100101 +
#271
1%
b011111100001111001101100 '
#272
b0010001000 #
0%
b00100001111101111000 )
b00000000010101101111 *
b0101101111 +
#273
1%
b100000010001111101101011 '
#274
b0010001001 #
0%
b00100010001101110111 )
b00000000010101111001 *
b0101111001 +
#275
1%
b100001100010000101101010 '
#276
b0010001010 #
0%
b00100010011101110110 )
b00000000010110000011 *
b0110000011 +
#277
1%
b100010010010001001101001 '
#278
b0010001011 #
0%
b00100010101101110101 )
b00000000010110001101 *
b0110001101 +
#279
1%
b100011100010010001101000 '
#280
b0010001100 #
0%
b00100010111101110100 )
b00000000010110011000 *
b0110011000 +
#281
1%
b100100110010010101100111 '
#282
b0010001101 #
0%
b00100011001101110011 )
b00000000010110100010 *
b0110100010 +
#283
1%
b100101100010011001100110 '
#284
b0010001110 #
0%
b00100011011101110010 )
b00000000010110101100 *
b0110101100 +
#285
1%
b100110110010100001100100 '
#286
b0010001111 #
0%
b00100011101101110001 )
b00000000010110110110 *
b0110110110 +
#287
1%
b100111100010100101100011 '
#288
b0010010000 #
0%
b00100011111101110000 )
b00000000010111000001 *
b0111000001 +
#289
1%
b101000110010101101100001 '
#290
b0010010001 #
0%
b00100100001101101111 )
b00000000010111001011 *
b0111001011 +
#291
1%
b101001100010110001011111 '
#292
b0010010010 #
0%
b00100100011101101110 )
b00000000010111010101 *
b0111010101 +
#293
1%
b101010110010111001011101 '
#294
b0010010011 #
0%
b00100100101101101101 )
b00000000010111011111 *
b0111011111 +
#295
1%
b101011100011000001011011 '
#296
b0010010100 #
0%
b00100100111101101100 )
b00000000010111101010 *
b0111101010 +
#297
1%
b101100100011001001011001 '
#298
b0010010101 #
0%
b00100101001101101011 )
b00000000010111110100 *
b0111110100 +
#299
1%
b101101110011010001010110 '
#300
b0010010110 #
0%
b00100101011101101010 )
b00000000010111111110 *
b0111111110 +
#301
1%
b101110100011011001010101 '
#302
b0010010111 #
0%
b00100101101101101001 )
b00000000011000001000 *
b1000001000 +
#303
1%
b101111100011100001010010 '
#304
b0010011000 #
0%
b00100101111101101000 )
b00000000011000010010 *
b1000010010 +
#305
1%
b110000010011101001010000 '
#306
b0010011001 #
0%
b00100110001101100111 )
b00000000011000011101 *
b1000011101 +
#307
1%
b110001010011110101001101 '
#308
b0010011010 #
0%
b00100110011101100110 )
b00000000011000100111 *
b1000100111 +
#309
1%
b110010000011111001001011 '
#310
b0010011011 #
0%
b00100110101101100101 )
b00000000011000110001 *
b1000110001 +
#311
1%
b110011000100000101001000 '
#312
b0010011100 #
0%
b00100110111101100100 )
b00000000011000111011 *
b1000111011 +
#313
1%
b110011110100010001000110 '
#314
b0010011101 #
0%
b00100111001101100011 )
b00000000011001000110 *
b1001000110 +
#315
1%
b110100100100011101000010 '
#316
b0010011110 #
0%
b00100111011101100010 )
b00000000011001010000 *
b1001010000 +
#317
1%
b110101100100101000111111 '
#318
b0010011111 #
0%
b00100111101101100001 )
b00000000011001011010 *
b1001011010 +
#319
1%
b110110010100110100111101 '
#320
b0010100000 #
0%
b00100111111101100000 )
b00000000011001100100 *
b1001100100 +
#321
1%
b110111000101000000111001 '
#322
b0010100001 #
0%
b00101000001101011111 )
b00000000011001101111 *
b1001101111 +
#323
1%
b110111100101001100110111 '
#324
b0010100010 #
0%
b00101000011101011110 )
b00000000011001111001 *
b1001111001 +
#325
1%
b111000100101011100110011 '
#326
b0010100011 #
0%
b00101000101101011101 )
b00000000011010000011 *
b1010000011 +
#327
1%
b111001000101101000110001 '
#328
b0010100100 #
0%
b00101000111101011100 )
b00000000011010001101 *
b1010001101 +
#329
1%
b111001100101111000101101 '
#330
b0010100101 #
0%
b00101001001101011011 )
b00000000011010010111 *
b1010010111 +
#331
1%
b111010000110000100101011 '
#332
b0010100110 #
0%
b00101001011101011010 )
b00000000011010100010 *
b1010100010 +
#333
1%
b111010110110010100100111 '
#334
b0010100111 #
0%
b00101001101101011001 )
b00000000011010101100 *
b1010101100 +
#335
1%
b111011010110101000100011 '
#336
b0010101000 #
0%
b00101001111101011000 )
b00000000011010110110 *
b1010110110 +
#337
1%
b111011110110110100100001 '
#338
b0010101001 #
0%
b00101010001101010111 )
b00000000011011000000 *
b1011000000 +
#339
1%
b111100010111001000011101 '
#340
b0010101010 #
0%
b00101010011101010110 )
b00000000011011001011 *
b1011001011 +
#341
1%
b111100100111010100011010 '
#342
b0010101011 #
0%
b00101010101101010101 )
b00000000011011010101 *
b1011010101 +
#343
1%
b111101000111101000010110 '
#344
b0010101100 #
0%
b00101010111101010100 )
b00000000011011011111 *
b1011011111 +
#345
1%
b111101010111111000010100 '
#346
b0010101101 #
0%
b00101011001101010011 )
b00000000011011101001 *
b1011101001 +
#347
1%
b111101111000001100010000 '
#348
b0010101110 #
0%
b00101011011101010010 )
b00000000011011110100 *
b1011110100 +
#349
1%
b111110001000100000001100 '
#350
b0010101111 #
0%
b00101011101101010001 )
b00000000011011111110 *
b1011111110 +
#351
1%
b111110011000110000001001 '
#352
b0010110000 #
0%
b00101011111101010000 )
b00000000011100001000 *
b1100001000 +
#353
1%
b111110101001000100000111 '
#354
b0010110001 #
0%
b00101100001101001111 )
b00000000011100010010 *
b1100010010 +
#355
1%
b111110101001010100000110 '
#356
b0010110010 #
0%
b00101100011101001110 )
b00000000011100011100 *
b1100011100 +
#357
1%
b111110111001101100000110 '
#358
b0010110011 #
0%
b00101100101101001101 )
b00000000011100100111 *
b1100100111 +
#359
1%
b111110111001111000000111 '
#360
b0010110100 #
0%
b00101100111101001100 )
b00000000011100110001 *
b1100110001 +
#361
1%
b111110111010010000001010 '
#362
b0010110101 #
0%
b00101101001101001011 )
b00000000011100111011 *
b1100111011 +
#363
1%
b111110111010100000001101 '
#364
b0010110110 #
0%
b00101101011101001010 )
b00000000011101000101 *
b1101000101 +
#365
1%
b111110111010111000010010 '
#366
b0010110111 #
0%
b00101101101101001001 )
b00000000011101010000 *
b1101010000 +
#367
1%
b111110111011001100011000 '
#368
b0010111000 #
0%
b00101101111101001000 )
b00000000011101011010 *
b1101011010 +
#369
1%
b111110111011011100011100 '
#370
b0010111001 #
0%
b00101110001101000111 )
b00000000011101100100 *
b1101100100 +
#371
1%
b111110101011110100100011 '
#372
b0010111010 #
0%
b00101110011101000110 )
b00000000011101101110 *
b1101101110 +
#373
1%
b111110101100000100101000 '
#374
b0010111011 #
0%
b00101110101101000101 )
b00000000011101111001 *
b1101111001 +
#375
1%
b111110011100011100101111 '
#376
b0010111100 #
0%
b00101110111101000100 )
b00000000011110000011 *
b1110000011 +
#377
1%
b111110001100101100110100 '
#378
b0010111101 #
0%
b00101111001101000011 )
b00000000011110001101 *
b1110001101 +
#379
1%
b111101111101000100111100 '
#380
b0010111110 #
0%
b00101111011101000010 )
b00000000011110010111 *
b1110010111 +
#381
1%
b111101101101010101000010 '
#382
b0010111111 #
0%
b00101111101101000001 )
b00000000011110100001 *
b1110100001 +
#383
1%
b111101001101101101001011 '
#384
b0011000000 #
0%
b00101111111101000000 )
b00000000011110101100 *
b1110101100 +
#385
1%
b111100111110000001010110 '
#386
b0011000001 #
0%
b00110000001100111111 )
b00000000011110110110 *
b1110110110 +
#387
1%
b111100101110010001011101 '
#388
b0011000010 #
0%
b00110000011100111110 )
b00000000011111000000 *
b1111000000 +
#389
1%
b111100011110100101101000 '
#390
b0011000011 #
0%
b00110000101100111101 )
b00000000011111001010 *
b1111001010 +
#391
1%
b111100011110110101110000 '
#392
b0011000100 #
0%
b00110000111100111100 )
b00000000011111010101 *
b1111010101 +
#393
1%
b111100011111001001111101 '
#394
b0011000101 #
0%
b00110001001100111011 )
b00000000011111011111 *
b1111011111 +
#395
1%
b111100101111010010000101 '
#396
b0011000110 #
0%
b00110001011100111010 )
b00000000011111101001 *
b1111101001 +
#397
1%
b111101011111100010010001 '
#398
b0011000111 #
0%
b00110001101100111001 )
b00000000011111110011 *
b1111110011 +
#399
1%
b111101111111101110011001 '
#400
b0011001000 #
0%
b00110001111100111000 )
b00000000011111111110 *
b1111111110 +
#401
1%
b111111001111111010100100 '
#402
b0011001001 #
0%
b00110010001100110111 )
b00000000100000001000 *
b0000001000 +
#403
1%
b000000000000000000000110 '
#404
b0011001010 #
0%
b00110010011100110110 )
b00000000100000010010 *
b0000010010 +
#405
1%
b000000010000000100001001 '
#406
b0011001011 #
0%
b00110010101100110101 )
b00000000100000011100 *
b0000011100 +
#407
1%
b000000100000001000010000 '
#408
b0011001100 #
0%
b00110010111100110100 )
b00000000100000100110 *
b0000100110 +
#409
1%
b000001000000001100010100 '
#410
b0011001101 #
0%
b00110011001100110011 )
b00000000100000110001 *
b0000110001 +
#411
1%
b000001100000010000011011 '
#412
b0011001110 #
0%
b00110011011100110010 )
b00000000100000111011 *
b0000111011 +
#413
1%
b000010000000011000011111 '
#414
b0011001111 #
0%
b00110011101100110001 )
b00000000100001000101 *
b0001000101 +
#415
1%
b000010110000011100100110 '
#416
b0011010000 #
0%
b00110011111100110000 )
b00000000100001001111 *
b0001001111 +
#417
1%
b000011100000100000101010 '
#418
b0011010001 #
0%
b00110100001100101111 )
b00000000100001011010 *
b0001011010 +
#419
1%
b000100100000101000110010 '
#420
b0011010010 #
0%
b00110100011100101110 )
b00000000100001100100 *
b0001100100 +
#421
1%
b000101100000101100111001 '
#422
b0011010011 #
0%
b00110100101100101101 )
b00000000100001101110 *
b0001101110 +
#423
1%
b000110010000101100111110 '
#424
b0011010100 #
0%
b00110100111100101100 )
b00000000100001111000 *
b0001111000 +
#425
1%
b000111010000110001000101 '
#426
b0011010101 #
0%
b00110101001100101011 )
b00000000100010000010 *
b0010000010 +
#427
1%
b001000000000110001001010 '
#428
b0011010110 #
0%
b00110101011100101010 )
b00000000100010001101 *
b0010001101 +
#429
1%
b001001100000101101010000 '
#430
b0011010111 #
0%
b00110101101100101001 )
b00000000100010010111 *
b0010010111 +
#431
1%
b001010010000101101010100 '
#432
b0011011000 #
0%
b00110101111100101000 )
b00000000100010100001 *
b0010100001 +
#433
1%
b001011100000101001011010 '
#434
b0011011001 #
0%
b00110110001100100111 )
b00000000100010101011 *
b0010101011 +
#435
1%
b001100100000100101011101 '
#436
b0011011010 #
0%
b00110110011100100110 )
b00000000100010110110 *
b0010110110 +
#437
1%
b001101110000100101100001 '
#438
b0011011011 #
0%
b00110110101100100101 )
b00000000100011000000 *
b0011000000 +
#439
1%
b001111000000100101100101 '
#440
b0011011100 #
0%
b00110110111100100100 )
b00000000100011001010 *
b0011001010 +
#441
1%
b010000000000100101100110 '
#442
b0011011101 #
0%
b00110111001100100011 )
b00000000100011010100 *
b0011010100 +
#443
1%
b010001010000101001101001 '
#444
b0011011110 #
0%
b00110111011100100010 )
b00000000100011011111 *
b0011011111 +
#445
1%
b010010000000101101101010 '
#446
b0011011111 #
0%
b00110111101100100001 )
b00000000100011101001 *
b0011101001 +
#447
1%
b010011010000110001101011 '
#448
b0011100000 #
0%
b00110111111100100000 )
b00000000100011110011 *
b0011110011 +
#449
1%
b010100000000110101101100 '
#450
b0011100001 #
0%
b00111000001100011111 )
b00000000100011111101 *
b0011111101 +
#451
1%
b010101010000111101101101 '
#452
b0011100010 #
0%
b00111000011100011110 )
b00000000100100000111 *
b0100000111 +
#453
1%
b010110000001000001101101 '
#454
b0011100011 #
0%
b00111000101100011101 )
b00000000100100010010 *
b0100010010 +
#455
1%
b010111010001001001101110 '
#456
b0011100100 #
0%
b00111000111100011100 )
b00000000100100011100 *
b0100011100 +
#457
1%
b011000100001010001101110 '
#458
b0011100101 #
0%
b00111001001100011011 )
b00000000100100100110 *
b0100100110 +
#459
1%
b011001010001010101101110 '
